tests/vectors/test_vcd.sv
module mod (
    input logic clk,
    input logic[15:0] a,
    output logic[15:0] b
);

always_ff @(posedge clk) begin
    b <= a;
end

endmodule


module top;

logic clk;
logic [15:0] a, b;

mod dut (.*);

initial clk = 0;
always clk = #5 ~clk;

initial begin
    $dumpfile("test_vcd.vcd");
    $dumpvars(0, top);
    for (int i = 0; i < 10; i++) begin
        a = i;
        @(posedge clk);
    end
    $finish;
end

endmodule

tests/vectors/test_vcd.vcd
$date
    Mar  6, 2021  20:56:34
$end
$version
    TOOL:	xmsim(64)	20.09-s007
$end
$timescale
    1 ns
$end

$scope module top $end
$var reg       1 !    clk $end
$var reg      16 "    a [15:0] $end
$var reg      16 #    b [15:0] $end

$scope module dut $end
$var wire      1 $    clk  $end
$var wire     16 %    a [15:0] $end
$var reg      16 &    b [15:0] $end
$upscope $end

$upscope $end

$enddefinitions $end
$dumpvars
0!
b0 "
bx #
0$
b0 %
bx &
$end
#5
1!
b1 "
b1 %
1$
b1 &
b1 #
#10
0!
0$
#15
1!
b10 "
b10 %
1$
b10 &
b10 #
#20
0!
0$
#25
1!
b11 "
b11 %
1$
b11 &
b11 #
#30
0!
0$
#35
1!
b100 "
b100 %
1$
b100 &
b100 #
#40
0!
0$
#45
1!
b101 "
b101 %
1$
b101 &
b101 #
#50
0!
0$
#55
1!
b110 "
b110 %
1$
b110 &
b110 #
#60
0!
0$
#65
1!
b111 "
b111 %
1$
b111 &
b111 #
#70
0!
0$
#75
1!
b1000 "
b1000 %
1$
b1000 &
b1000 #
#80
0!
0$
#85
1!
b1001 "
b1001 %
1$
b1001 &
b1001 #
